{
  "TAB_NAMES": [
    "HPI",
    "Patient History",
    "Review of Systems",
    "Physical Exam",
    "Plan",
    "Generate Note"
  ],
  "CONDITIONS": [
    "Type II Diabetes",
    "Myocardial Infarction",
    "Hypertension",
    "Hypercholesteremia",
    "Depression",
    "HIV"
  ],
  "MEDICAL_HISTORY": {
    "STATE": {
      "0": {
        "Condition": "Type II Diabetes",
        "Yes": false,
        "No": false,
        "Onset": "",
        "Comments": ""
      },
      "1": {
        "Condition": "Myocardial Infarction",
        "Yes": false,
        "No": false,
        "Onset": "",
        "Comments": ""
      },
      "2": {
        "Condition": "Hypertension",
        "Yes": false,
        "No": false,
        "Onset": "",
        "Comments": ""
      },
      "3": {
        "Condition": "Hypercholesteremia",
        "Yes": false,
        "No": false,
        "Onset": "",
        "Comments": ""
      },
      "4": {
        "Condition": "Depression",
        "Yes": false,
        "No": false,
        "Onset": "",
        "Comments": ""
      },
      "5": {
        "Condition": "HIV",
        "Yes": false,
        "No": false,
        "Onset": "",
        "Comments": ""
      }
    }
  },
  "FAMILY_HISTORY": {
    "STATE": {
      "0": {
        "Condition": "Type II Diabetes",
        "Yes": false,
        "No": false,
        "Family Member": [],
        "Cause of Death": [],
        "Comments": ""
      },
      "1": {
        "Condition": "Myocardial Infarction",
        "Yes": false,
        "No": false,
        "Family Member": [],
        "Cause of Death": [],
        "Comments": ""
      },
      "2": {
        "Condition": "Hypertension",
        "Yes": false,
        "No": false,
        "Family Member": [],
        "Cause of Death": [],
        "Comments": ""
      },
      "3": {
        "Condition": "Hypercholesteremia",
        "Yes": false,
        "No": false,
        "Family Member": [],
        "Cause of Death": [],
        "Comments": ""
      },
      "4": {
        "Condition": "Depression",
        "Yes": false,
        "No": false,
        "Family Member": [],
        "Cause of Death": [],
        "Comments": ""
      },
      "5": {
        "Condition": "HIV",
        "Yes": false,
        "No": false,
        "Family Member": [],
        "Cause of Death": [],
        "Comments": ""
      }
    }
  },
  "SOCIAL_HISTORY": {
    "SUBSTANCE_USE_CONTENT_HEADER": "Substance Use",
    "SECONDARY_FIELDS": [
      "Living Situation",
      "Employment",
      "Diet",
      "Exercise"
    ],
    "SUBSTANCE_USE_FIELDS": {
      "Tobacco": {
        "condition": "Tobacco",
        "firstField": "Packs/Day",
        "secondField": "Number of Years",
        "thirdField": "Products Used",
        "quitYear": "Quit Year"
      },
      "Alcohol": {
        "condition": "Alcohol",
        "firstField": "Drink Type",
        "secondField": "Drink Size",
        "thirdField": "# Per Week",
        "quitYear": "Quit Year"
      },
      "Substance Abuse": {
        "condition": "Substance Abuse",
        "firstField": "Drug Name",
        "secondField": "Mode of Delivery",
        "thirdField": "# Per Week",
        "quitYear": "Quit Year"
      }
    },
    "STATE": {
      "Alcohol": {
        "Yes": false,
        "In the Past": false,
        "Never Used": false,
        "Drinks Type": "",
        "Drink Size": "",
        "# Per Week": "",
        "Quit Year": "",
        "Comments": ""
      },
      "Tobacco": {
        "Yes": false,
        "In the Past": false,
        "Never Used": false,
        "Packs/Day": "",
        "Number of Years": "",
        "Products Used": "",
        "Quit Year": "",
        "Comments": ""
      },
      "Substance Abuse": {
        "Yes": false,
        "In the Past": false,
        "Never Used": false,
        "Drug Name": "",
        "Mode of Delivery": "",
        "# Per Week": "",
        "Quit Year": "",
        "Comments": ""
      },
      "Living Situation": "",
      "Employment": "",
      "Diet": "",
      "Exercise": ""
    }
  },
  "ALLERGIES": {
    "fields": [
      "Inciting Agent",
      "Reaction",
      "Comments"
    ],
    "STATE": {
      "Inciting Agent": "",
      "Reaction": "",
      "Comments": ""
    }
  }
}